ALU.v
module testbed;//for testing the alu

    reg [7:0] DATA1,DATA2;
    reg [2:0] SELECT; //creating registers and wires
    wire [7:0] RESULT;

    initial begin
        $monitor($time," result : %b",RESULT);//monitering the changes in result
        $dumpfile("alu_wavedata.vcd");//wavedata dumpfile to be examined with GTKwave
        $dumpvars(0,testbed);//dumpng all the variables in the testbed 
    end

    alu myALU(DATA1,DATA2,RESULT,SELECT);//instanciating the alu module

    initial begin
        DATA1 = 8'b1000_0001;
        DATA2 = 8'b0100_1110;
    end

    initial begin
        #10
        SELECT = 3'b001;//add signal
        DATA1 = 8'b0000_0001;
        DATA2 = 8'b0000_0011;
    end

    initial begin
        #15
        SELECT = 3'b010;//and signal
        DATA1 = 8'b1101_0101;
        DATA2 = 8'b1110_1010;
    end

    initial begin
        #20
        SELECT = 3'b011;//or signal
        DATA1 = 8'b0000_0001;
        DATA2 = 8'b0000_0010;
    end
    
    initial begin
        #25
        SELECT = 3'b000;
        DATA1 = 8'b1000_0001;
        DATA2 = 8'b0111_1110;
    end

    initial begin//finishing the simulation
        #100 $finish;
    end

endmodule

module alu(DATA1,DATA2,RESULT,SELECT);

    input  [7:0] DATA1 ;
    input  [7:0] DATA2 ;//defining inputs and outputs all wires exept for the result register
    input  [2:0] SELECT ;
    output reg [7:0] RESULT;//has to be register type, as RESULT is assigned values in an always @ block

    wire [7:0] forward_out,add_out,and_out,or_out;//wires inside the alu

    FORWARD Forward(DATA2,forward_out);//iinstantiating modules with individual output wires for each
    ADD Add(DATA1,DATA2,add_out);
    AND And(DATA1,DATA2,and_out) ;
    OR Or(DATA1,DATA2,or_out) ;

   always @ (DATA1,DATA2,SELECT) begin//run whenever inputs are changed

    case (SELECT)

    3'b000 :  RESULT = forward_out;//assigning the coresponding outputs acording to the SELECT signal
    3'b001 :  RESULT = add_out;
    3'b010 :  RESULT = and_out;
    3'b011 :  RESULT = or_out;
    default :  RESULT =forward_out;
    
    endcase

    end

endmodule
    
module FORWARD(DATA2,RESULT);//module for forwarding the data from port two to RESULT

    input [7:0] DATA2 ;
    output [7:0] RESULT;
    assign #1 RESULT = DATA2;//continuous assigning of valules to the wire RESULT with an artifitial delay

endmodule

module ADD(DATA1,DATA2,RESULT);//module to add two 8bit data values

    input [7:0] DATA1 ;
    input [7:0] DATA2 ;
    output [7:0] RESULT;

    assign #2 RESULT = DATA1 + DATA2;//addiing the data and continuesly assigning the wire RESULT with an artifitial delay

endmodule

module AND(DATA1,DATA2,RESULT) ;//module for bitwise and operation

    input [7:0] DATA1 ;
    input [7:0] DATA2 ;
    output [7:0] RESULT;

    assign #1 RESULT = DATA1 & DATA2;//ANDing the data and continuesly assigning the wire RESULT with an artifitial delay

endmodule

module OR(DATA1,DATA2,RESULT) ;//module for bitwise or operation

    input [7:0] DATA1 ;
    input [7:0] DATA2 ;
    output [7:0] RESULT;

    assign #1 RESULT = DATA1 | DATA2;//ORing the data and continuesly assigning the wire RESULT with an artifitial delay

endmodule

alu_wavedata.vcd
$date
	Tue Oct 20 21:11:46 2020
$end
$version
	Icarus Verilog
$end
$timescale
	1s
$end
$scope module testbed $end
$var wire 8 ! RESULT [7:0] $end
$var reg 8 " DATA1 [7:0] $end
$var reg 8 # DATA2 [7:0] $end
$var reg 3 $ SELECT [2:0] $end
$scope module myALU $end
$var wire 8 % DATA1 [7:0] $end
$var wire 8 & DATA2 [7:0] $end
$var wire 3 ' SELECT [2:0] $end
$var wire 8 ( or_out [7:0] $end
$var wire 8 ) forward_out [7:0] $end
$var wire 8 * and_out [7:0] $end
$var wire 8 + add_out [7:0] $end
$var reg 8 , RESULT [7:0] $end
$scope module Add $end
$var wire 8 - DATA1 [7:0] $end
$var wire 8 . DATA2 [7:0] $end
$var wire 8 / RESULT [7:0] $end
$upscope $end
$scope module And $end
$var wire 8 0 DATA1 [7:0] $end
$var wire 8 1 DATA2 [7:0] $end
$var wire 8 2 RESULT [7:0] $end
$upscope $end
$scope module Forward $end
$var wire 8 3 DATA2 [7:0] $end
$var wire 8 4 RESULT [7:0] $end
$upscope $end
$scope module Or $end
$var wire 8 5 DATA1 [7:0] $end
$var wire 8 6 DATA2 [7:0] $end
$var wire 8 7 RESULT [7:0] $end
$upscope $end
$upscope $end
$upscope $end
$enddefinitions $end
#0
$dumpvars
bx 7
b1001110 6
b10000001 5
bx 4
b1001110 3
bx 2
b1001110 1
b10000001 0
bx /
b1001110 .
b10000001 -
bx ,
bx +
bx *
bx )
bx (
bx '
b1001110 &
b10000001 %
bx $
b1001110 #
b10000001 "
bx !
$end
#1
b11001111 (
b11001111 7
b0 *
b0 2
b1001110 )
b1001110 4
#2
b11001111 +
b11001111 /
#10
b11001111 !
b11001111 ,
b1 $
b1 '
#15
b0 !
b0 ,
b10 $
b10 '
#20
b11001111 !
b11001111 ,
b11 $
b11 '
#25
b1001110 !
b1001110 ,
b1111110 #
b1111110 &
b1111110 .
b1111110 1
b1111110 3
b1111110 6
b0 $
b0 '
#26
b11111111 (
b11111111 7
b1111110 )
b1111110 4
#27
b11111111 +
b11111111 /
