CPU.v
`include "REG_FILE.v"
`include "ALU.v"

module cpu(PC, INSTRUCTION, CLK, RESET);

    input CLK,RESET;
    output reg [31:0] PC;
    input [31:0] INSTRUCTION; 

    wire WRITEENABLE;
    wire [31:0] PC_NEXT;
    wire [2:0] ALUOP;
    wire COMPLEMENT_FLAG;
    wire IMMEDIATE_FALG;
    wire [7:0] REGOUT1;
    wire [7:0] REGOUT2;
    wire [7:0] COMPLEMENTED_OUT;
    reg [7:0] COMPLEMENT_MUX_OUT;
    reg [7:0] IMMEDIATE_MUX_OUT;
    wire [7:0] IMMEDIATE;
    wire [7:0] ALU_RESULT;

    wire [2:0] READREG1;
    wire [2:0] READREG2;
    wire [2:0] WRITEREG;

    assign WRITEREG = INSTRUCTION[23:16];
    assign READREG1 = INSTRUCTION[15:8];
    assign READREG2 = INSTRUCTION[7:0];
    assign IMMEDIATE = INSTRUCTION[7:0];
	
    control_unit ctrlUnit(INSTRUCTION,WRITEENABLE,ALUOP,COMPLEMENT_FLAG,IMMEDIATE_FALG);
    pc_adder pcNext(PC,PC_NEXT);
    reg_file regFile(ALU_RESULT,REGOUT1,REGOUT2,WRITEREG,READREG1,READREG2, WRITEENABLE, CLK, RESET);
    alu ALU(REGOUT1,IMMEDIATE_MUX_OUT,ALU_RESULT,ALUOP);
    twosComplement complementor(REGOUT2,COMPLEMENTED_OUT);

    always @ (REGOUT2,COMPLEMENTED_OUT,COMPLEMENT_FLAG) begin//mux 1
        case (COMPLEMENT_FLAG)
            0 : COMPLEMENT_MUX_OUT <= REGOUT2;
            1 : COMPLEMENT_MUX_OUT <= COMPLEMENTED_OUT;
        endcase
    end

    always @ (COMPLEMENT_MUX_OUT,IMMEDIATE_FALG,IMMEDIATE) begin//mux 2
        case (IMMEDIATE_FALG)
            0 : IMMEDIATE_MUX_OUT <= COMPLEMENT_MUX_OUT;
            1 : IMMEDIATE_MUX_OUT <= IMMEDIATE;
        endcase
    end

    always @ (posedge CLK) begin
        case(RESET)
            0 : PC <= #1 PC_NEXT;
            1 : PC <= #1 32'b0;
        endcase
    end


endmodule


module control_unit(INSTRUCTION,WRITEENABLE,ALUOP,COMPLEMENT_FLAG,IMMEDIATE_FALG);
    
    input [31:0] INSTRUCTION;
    output reg WRITEENABLE;
    output reg [2:0] ALUOP;
    output reg COMPLEMENT_FLAG;
    output reg IMMEDIATE_FALG;

    wire [7:0] opcode;
    assign #1 opcode = INSTRUCTION[31:24];//decoding delay

    always @ (opcode) begin
        case (opcode)
            8'b0000_0000 : begin
                WRITEENABLE <= 1;//
                COMPLEMENT_FLAG <= 0;
                IMMEDIATE_FALG <=1;
                ALUOP <= 3'b000;//loadi==>foward                  
            end
            8'b0000_0001 : begin               
                WRITEENABLE <= 1;
                COMPLEMENT_FLAG <=0;
                IMMEDIATE_FALG <=0;
                ALUOP = 3'b000;//mov==>foward ;stall opcode until the register reading
            end
            8'b0000_0010 : begin                 
                WRITEENABLE <= 1;
                COMPLEMENT_FLAG <=0;
                IMMEDIATE_FALG <=0;
                ALUOP <=  3'b001;//add==>add ;stall opcode until the register reading
            end
            8'b0000_0011 : begin                
                WRITEENABLE <= 1;
                COMPLEMENT_FLAG <=1;
                IMMEDIATE_FALG <=0;
                ALUOP <=  3'b001;//sub==>add ;stall opcode until the register reading and 2s complementing
            end
            8'b0000_0100 : begin               
                WRITEENABLE <= 1;
                COMPLEMENT_FLAG <=0;
                IMMEDIATE_FALG <=0;
                ALUOP <= 3'b010;//and==>and  ;stall opcode until the register reading 
            end
            8'b0000_0101 : begin            
                WRITEENABLE <= 1;
                COMPLEMENT_FLAG <=0;
                IMMEDIATE_FALG <=0;
                ALUOP <=  3'b011;//or==>or ;stall opcode until the register reading    
            end
            default : begin              
                WRITEENABLE <= 0;
                COMPLEMENT_FLAG <=0;
                IMMEDIATE_FALG <=0;
                ALUOP <= 3'b000;    
            end
        endcase 

           /* 8'b0000_0110 : ALUOP = 3'b001;//j==>add
            8'b0000_0111 : ALUOP = 3'b001;//sub==>add
            8'b0000_1000 : ALUOP = 3'b001;//sub==>add
            8'b0000_1001 : ALUOP = 3'b001;//sub==>add
            8'b0000_1010 : ALUOP = 3'b001;//sub==>add
            8'b0000_1011 : ALUOP = 3'b001;//sub==>add
        
            char *op_loadi 	= "00000000";
            char *op_mov 	= "00000001";
            char *op_add 	= "00000010";
            char *op_sub 	= "00000011";
            char *op_and 	= "00000100";
            char *op_or 	= "00000101";
            char *op_j		= "00000110";
            char *op_beq	= "00000111";
            char *op_lwd 	= "00001000";
            char *op_lwi 	= "00001001";
            char *op_swd 	= "00001010";
            char *op_swi 	= "00001011";
            */

        
    end

endmodule

module twosComplement(REGOUT2,COMPLEMENTED_OUT);
    input signed [7:0] REGOUT2;
    output signed [7:0] COMPLEMENTED_OUT;

    assign #1 COMPLEMENTED_OUT = - REGOUT2;

endmodule

module pc_adder(PC,PC_NEXT);
    input [31:0] PC;
    output [31:0] PC_NEXT;

    assign #2 PC_NEXT = PC + 32'b0100;//MSBs are filled with 0s

endmodule

ALU.v
/*module testbed;//for testing the alu

    reg [7:0] DATA1,DATA2;
    reg [2:0] SELECT; //creating registers and wires
    wire [7:0] RESULT;

    initial begin
        $monitor($time,"select = %b data1 = %b data2 = %b result : %b",SELECT,DATA1,DATA2,RESULT);//monitering the changes in result
        $dumpfile("alu_wavedata.vcd");//wavedata dumpfile to be examined with GTKwave
        $dumpvars(0,testbed);//dumpng all the variables in the testbed 
    end

    alu myALU(DATA1,DATA2,RESULT,SELECT);//instanciating the alu module

    initial begin
        DATA1 = 8'b1000_0001;
        DATA2 = 8'b0100_1110;
    end

    initial begin
        #10
        SELECT = 3'b001;//add signal
        DATA1 = 8'b0000_0001;
        DATA2 = 8'b0000_0011;
    end

    initial begin
        #15
        SELECT = 3'b010;//and signal
        DATA1 = 8'b1101_0101;
        DATA2 = 8'b1110_1010;
    end

    initial begin
        #20
        SELECT = 3'b011;//or signal
        DATA1 = 8'b0000_0001;
        DATA2 = 8'b0000_0010;
    end
    
    initial begin
        #25
        SELECT = 3'b000;
        DATA1 = 8'b1000_0001;
        DATA2 = 8'b0111_1110;
    end

    initial begin//finishing the simulation
        #100 $finish;
    end

endmodule*/

module alu(DATA1,DATA2,RESULT,SELECT);

    input  [7:0] DATA1 ;
    input  [7:0] DATA2 ;//defining inputs and outputs all wires exept for the result register
    input  [2:0] SELECT ;
    output reg [7:0] RESULT;//has to be register type, as RESULT is assigned values in an always @ block

    wire [7:0] forward_out,add_out,and_out,or_out;//wires inside the alu

    FORWARD Forward(DATA2,forward_out);//instantiating modules with individual output wires for each
    ADD Add(DATA1,DATA2,add_out);
    AND And(DATA1,DATA2,and_out) ;
    OR Or(DATA1,DATA2,or_out) ;

   always @ (SELECT,forward_out,add_out,and_out,or_out) begin//run whenever inputs are changed

    case (SELECT)

    3'b000 :  RESULT = forward_out;//assigning the coresponding outputs acording to the SELECT signal
    3'b001 :  RESULT = add_out;
    3'b010 :  RESULT = and_out;
    3'b011 :  RESULT = or_out;
    default :  RESULT =forward_out;
    
    endcase

    end

endmodule
    
module FORWARD(DATA2,RESULT);//module for forwarding the data from port two to RESULT

    input [7:0] DATA2 ;
    output [7:0] RESULT;

    assign #1 RESULT = DATA2;//continuous assigning of valules to the wire RESULT with an artifitial delay

endmodule

module ADD(DATA1,DATA2,RESULT);//module to add two 8bit data values

    input [7:0] DATA1 ;
    input [7:0] DATA2 ;
    output [7:0] RESULT;

    assign #2 RESULT = DATA1 + DATA2;//addiing the data and continuesly assigning the wire RESULT with an artifitial delay

endmodule

module AND(DATA1,DATA2,RESULT) ;//module for bitwise and operation

    input [7:0] DATA1 ;
    input [7:0] DATA2 ;
    output [7:0] RESULT;

    assign #1 RESULT = DATA1 & DATA2;//ANDing the data and continuesly assigning the wire RESULT with an artifitial delay

endmodule

module OR(DATA1,DATA2,RESULT) ;//module for bitwise or operation

    input [7:0] DATA1 ;
    input [7:0] DATA2 ;
    output [7:0] RESULT;

    assign #1 RESULT = DATA1 | DATA2;//ORing the data and continuesly assigning the wire RESULT with an artifitial delay

endmodule

REG_FILE.v
/*
module testbed;//for testing the reg_file
    reg [7:0] IN;
    reg [2:0] INADDRESS,OUT1ADDRESS,OUT2ADDRESS;//creating registers and wires
    reg WRITE, CLK, RESET;
    wire [7:0] OUT1,OUT2;

    initial begin
        $monitor($time," OUT1 : %b OUT2 : %b",OUT1,OUT2);//monitering the changes in results
        $dumpfile("regfile_wavedata.vcd");//wavedata dumpfile to be examined with GTKwave
        $dumpvars(0,testbed);//dumpng all the variables in the testbed 
    end

    reg_file myreg(IN,OUT1,OUT2,INADDRESS,OUT1ADDRESS,OUT2ADDRESS, WRITE, CLK, RESET);//instanciating the register file module


    initial begin//creating a clock signal that flips every 10 time units forever 
        CLK = 1'b0;
        forever #10 CLK = ~CLK;	
    end

    
    initial begin

		Testing the RESET
		-----------------
		The clock goes up at t = 10. Therefore, the registers should be reset t = 10.
		Since reading has a delay of 2 time units, OUT1 and OUT2 should be 0 at t=12.
	
        #5
        RESET = 1;
        WRITE = 0;
        OUT1ADDRESS = 3'b000;
        OUT2ADDRESS = 3'b001; 
        
		
    end

    The register starts to write 8'b00011111 in the register 3'b010 at t=30. Since writing has a delay of 1 time units,
    the value should be written into the register at t=31.When the value of the register is read the OUT1 should be 
    8'b00010001 at t = 33. Since the OUT2ADDRESS did't change the value should be 8'b00000000.

    initial begin 
        #25
        RESET =0;
        WRITE = 1;
        IN = 8'b0001_1111;
        INADDRESS  = 3'b010;
        OUT1ADDRESS = 3'b010;
    end
 
     
    Making sure the register doesn't work at a negative edge of the clock.
    There is a negative edge of the clock at t=40. Even though the WRITE is enabled, the writing process does not take placa.
    So at t = 39+2 = 41 , OUT1 and OUT2 should be 8b'00000000.
    
    
    initial begin 
        #39
        WRITE = 1;
        IN = 8'b0000_1111;
        INADDRESS  = 3'b011;
        OUT1ADDRESS = 3'b011;
    end
    
    
    //Writing to a register and Reading it (using the OUT2)

    initial begin 
        #45
        WRITE = 1;
        IN = 8'b0101_0101;
        INADDRESS  = 3'b100;
		OUT2ADDRESS = 3'b100;
    end
 
	
    initial begin
        #70
        INADDRESS = 3'b010;
        IN = 8'b1111_1111;
        OUT2ADDRESS  = 3'b010;
         
    end
    
  
    initial begin//finishing the simulation
        #100
        $finish;
    end

endmodule
*/

module reg_file(IN,OUT1,OUT2,INADDRESS,OUT1ADDRESS,OUT2ADDRESS, WRITE, CLK, RESET);
    input [7:0] IN;
    output [7:0] OUT1;
    output [7:0] OUT2;
    input [2:0] INADDRESS;//defining inputs and outputs
    input WRITE;
    input CLK;
    input RESET;
    input [2:0] OUT1ADDRESS;
    input [2:0] OUT2ADDRESS;

    reg [7:0] REG_FILE [7:0] ;//creating the registers

    integer i ;

    assign #2 OUT1 = REG_FILE[OUT1ADDRESS] ;//continuously assigning the values in the regisers to output ports with a delay

    assign #2 OUT2 = REG_FILE[OUT2ADDRESS] ;

    always @ (posedge CLK) begin//at the positive edge of the clock signal
        if (RESET) begin//if reset signal is enabled, assign registers to  all zeros
            for (i=0;i<8;i++) 
                REG_FILE[i] <= #1 8'b0000_0000;
        end else if (WRITE) begin//if the reset is not enabled and the write is enabled write IN value to the relevent register
            #1 REG_FILE[INADDRESS] <=  IN;
        end
    end

endmodule

cpu_tb.v
// Computer Architecture (CO224) - Lab 05
// Design: Testbench of Integrated CPU of Simple Processor
// Author: Kisaru Liyanage
`include "CPU.v"

module cpu_tb;

    reg CLK, RESET;
    wire [31:0] PC;
    wire [31:0] INSTRUCTION;
    //wire [31:0] CPU_INSTRUCTION;
    reg [7:0] instr_mem[0:1023];

/*//this works too but need a wire to be passed to the cpu and a reg to be assigned
    always @ (PC,INSTRUCTION) begin
        INSTRUCTION[31:24] <= #2 instr_mem[PC];
        INSTRUCTION[23:16] <= #2 instr_mem[PC+32'b0001];
        INSTRUCTION[15:8] <= #2 instr_mem[PC+32'b0010];
        INSTRUCTION[7:0] <= #2 instr_mem[PC+32'b0011];
    end
*/

    assign #2 INSTRUCTION[7:0] = instr_mem[PC];//is it okay to do continuous assignment with a variable index??
    assign #2 INSTRUCTION[15:8] = instr_mem[PC+32'b0001];//works fine but practically makes no sense to me  
    assign #2 INSTRUCTION[23:16] = instr_mem[PC+32'b0010];
    assign #2 INSTRUCTION[31:24] = instr_mem[PC+32'b0011];
    //assign CPU_INSTRUCTION = INSTRUCTION;

    /* 
    ------------------------
     SIMPLE INSTRUCTION MEM
    ------------------------
    */
    
    // TODO: Initialize an array of registers (8x1024) named 'instr_mem' to be used as instruction memory
    
    // TODO: Create combinational logic to support CPU instruction fetching, given the Program Counter(PC) value 
    //       (make sure you include the delay for instruction fetching here)
    
    initial
    begin
        // Initialize instruction memory with the set of instructions you need execute on CPU
        
        // METHOD 1: manually loading instructions to instr_mem
/*
        {instr_mem[10'd3], instr_mem[10'd2], instr_mem[10'd1], instr_mem[10'd0]} = 32'b00000000000001000000000000000101;
        {instr_mem[10'd7], instr_mem[10'd6], instr_mem[10'd5], instr_mem[10'd4]} = 32'b00000000000000100000000000001001;
        {instr_mem[10'd11], instr_mem[10'd10], instr_mem[10'd9], instr_mem[10'd8]} = 32'b00000010000001100000010000000010;
        */
        // METHOD 2: loading instr_mem content from instr_mem.mem file
        $readmemb("instr_mem.mem", instr_mem);
    end
    
    /* 
    -----
     CPU
    -----
    */
    cpu mycpu(PC, INSTRUCTION, CLK, RESET);

    initial
    begin
    
        // generate files needed to plot the waveform using GTKWave
        $dumpfile("cpu_wavedata.vcd");
		$dumpvars(0, cpu_tb);
       // $monitor($time,"cmplmt_falg = %b immdte_flag=%b",COMPLEMENT_FLAG,IMMEDIATE_FLAG);
        
        CLK = 1'b0;
        RESET = 1'b1;
        #5
        RESET = 1'b0;
        
        // TODO: Reset the CPU (by giving a pulse to RESET signal) to start the program execution
        
        // finish simulation after some time
        #500
        $finish;
        
    end
    
    // clock signal generation
    always
        #4 CLK = ~CLK;
        

endmodule

cpu_wavedata.vcd
$date
	Tue Oct 27 20:51:49 2020
$end
$version
	Icarus Verilog
$end
$timescale
	1s
$end
$scope module cpu_tb $end
$var wire 32 ! PC [31:0] $end
$var wire 32 " INSTRUCTION [31:0] $end
$var reg 1 # CLK $end
$var reg 1 $ RESET $end
$scope module mycpu $end
$var wire 1 # CLK $end
$var wire 32 % INSTRUCTION [31:0] $end
$var wire 1 $ RESET $end
$var wire 3 & WRITEREG [2:0] $end
$var wire 1 ' WRITEENABLE $end
$var wire 8 ( REGOUT2 [7:0] $end
$var wire 8 ) REGOUT1 [7:0] $end
$var wire 3 * READREG2 [2:0] $end
$var wire 3 + READREG1 [2:0] $end
$var wire 32 , PC_NEXT [31:0] $end
$var wire 1 - IMMEDIATE_FALG $end
$var wire 8 . IMMEDIATE [7:0] $end
$var wire 1 / COMPLEMENT_FLAG $end
$var wire 8 0 COMPLEMENTED_OUT [7:0] $end
$var wire 8 1 ALU_RESULT [7:0] $end
$var wire 3 2 ALUOP [2:0] $end
$var reg 8 3 COMPLEMENT_MUX_OUT [7:0] $end
$var reg 8 4 IMMEDIATE_MUX_OUT [7:0] $end
$var reg 32 5 PC [31:0] $end
$scope module ALU $end
$var wire 8 6 DATA2 [7:0] $end
$var wire 8 7 or_out [7:0] $end
$var wire 8 8 forward_out [7:0] $end
$var wire 8 9 and_out [7:0] $end
$var wire 8 : add_out [7:0] $end
$var wire 3 ; SELECT [2:0] $end
$var wire 8 < DATA1 [7:0] $end
$var reg 8 = RESULT [7:0] $end
$scope module Add $end
$var wire 8 > DATA2 [7:0] $end
$var wire 8 ? RESULT [7:0] $end
$var wire 8 @ DATA1 [7:0] $end
$upscope $end
$scope module And $end
$var wire 8 A DATA2 [7:0] $end
$var wire 8 B RESULT [7:0] $end
$var wire 8 C DATA1 [7:0] $end
$upscope $end
$scope module Forward $end
$var wire 8 D DATA2 [7:0] $end
$var wire 8 E RESULT [7:0] $end
$upscope $end
$scope module Or $end
$var wire 8 F DATA2 [7:0] $end
$var wire 8 G RESULT [7:0] $end
$var wire 8 H DATA1 [7:0] $end
$upscope $end
$upscope $end
$scope module complementor $end
$var wire 8 I REGOUT2 [7:0] $end
$var wire 8 J COMPLEMENTED_OUT [7:0] $end
$upscope $end
$scope module ctrlUnit $end
$var wire 32 K INSTRUCTION [31:0] $end
$var wire 8 L opcode [7:0] $end
$var reg 3 M ALUOP [2:0] $end
$var reg 1 / COMPLEMENT_FLAG $end
$var reg 1 - IMMEDIATE_FALG $end
$var reg 1 ' WRITEENABLE $end
$upscope $end
$scope module pcNext $end
$var wire 32 N PC [31:0] $end
$var wire 32 O PC_NEXT [31:0] $end
$upscope $end
$scope module regFile $end
$var wire 1 # CLK $end
$var wire 8 P IN [7:0] $end
$var wire 3 Q INADDRESS [2:0] $end
$var wire 8 R OUT1 [7:0] $end
$var wire 3 S OUT1ADDRESS [2:0] $end
$var wire 8 T OUT2 [7:0] $end
$var wire 3 U OUT2ADDRESS [2:0] $end
$var wire 1 $ RESET $end
$var wire 1 ' WRITE $end
$var integer 32 V i [31:0] $end
$upscope $end
$upscope $end
$upscope $end
$enddefinitions $end
#0
$dumpvars
bx V
bx U
bx T
bx S
bx R
bx Q
bx P
bx O
bx N
bx M
bx L
bx K
bx J
bx I
bx H
bx G
bx F
bx E
bx D
bx C
bx B
bx A
bx @
bx ?
bx >
bx =
bx <
bx ;
bx :
bx 9
bx 8
bx 7
bx 6
bx 5
bx 4
bx 3
bx 2
bx 1
bx 0
x/
bx .
x-
bx ,
bx +
bx *
bx )
bx (
x'
bx &
bx %
1$
0#
bx "
bx !
$end
#4
b1000 V
1#
#5
b0 !
b0 5
b0 N
0$
#7
b100 &
b100 Q
b0 +
b0 S
b101 *
b101 U
b101 .
b100 ,
b100 O
b1000000000000000101 "
b1000000000000000101 %
b1000000000000000101 K
#8
b101 4
b101 6
b101 >
b101 A
b101 D
b101 F
b0 2
b0 ;
b0 M
1-
0/
1'
b0 L
0#
#9
b0 3
b101 1
b101 =
b101 P
b0x0x 9
b0x0x B
bx1x1 7
bx1x1 G
b101 8
b101 E
b0 )
b0 <
b0 @
b0 C
b0 H
b0 R
b0 (
b0 I
b0 T
#10
b101 7
b101 G
b0 9
b0 B
b0 0
b0 J
#11
b101 :
b101 ?
#12
1#
#13
b100 !
b100 5
b100 N
#15
b1001 4
b1001 6
b1001 >
b1001 A
b1001 D
b1001 F
b10 &
b10 Q
b1 *
b1 U
b1001 .
b1000 ,
b1000 O
b100000000000001001 "
b100000000000001001 %
b100000000000001001 K
#16
b1001 1
b1001 =
b1001 P
b1001 7
b1001 G
b1001 8
b1001 E
0#
#17
b1001 :
b1001 ?
#20
1#
#21
b1000 !
b1000 5
b1000 N
#23
b10 4
b10 6
b10 >
b10 A
b10 D
b10 F
b110 &
b110 Q
b100 +
b100 S
b10 *
b10 U
b10 .
b1100 ,
b1100 O
b10000001100000010000000010 "
b10000001100000010000000010 %
b10000001100000010000000010 K
#24
b0 4
b0 6
b0 >
b0 A
b0 D
b0 F
b1 2
b1 ;
b1 M
0-
b1001 1
b1001 =
b1001 P
b10 7
b10 G
b10 8
b10 E
b10 L
0#
#25
b1001 4
b1001 6
b1001 >
b1001 A
b1001 D
b1001 F
b1001 3
b0 7
b0 G
b0 8
b0 E
b101 )
b101 <
b101 @
b101 C
b101 H
b101 R
b1001 (
b1001 I
b1001 T
#26
b1 9
b1 B
b1001 8
b1001 E
b1101 7
b1101 G
b11110111 0
b11110111 J
#27
b1110 1
b1110 =
b1110 P
b1110 :
b1110 ?
#28
1#
#29
b1100 !
b1100 5
b1100 N
#31
b0 &
b0 Q
b0 +
b0 S
b110 *
b110 U
b110 .
b10000 ,
b10000 O
b1000000000000000000000110 "
b1000000000000000000000110 %
b1000000000000000000000110 K
#32
b1001 1
b1001 =
b1001 P
b0 2
b0 ;
b0 M
b1 L
0#
#33
b1110 4
b1110 6
b1110 >
b1110 A
b1110 D
b1110 F
b1110 3
b0 )
b0 <
b0 @
b0 C
b0 H
b0 R
b1110 (
b1110 I
b1110 T
#34
b1110 1
b1110 =
b1110 P
b1110 8
b1110 E
b1110 7
b1110 G
b0 9
b0 B
b11110010 0
b11110010 J
#36
1#
#37
b10000 !
b10000 5
b10000 N
#38
b1110 )
b1110 <
b1110 @
b1110 C
b1110 H
b1110 R
#39
b1 &
b1 Q
b1 *
b1 U
b1 .
b1110 9
b1110 B
b10100 ,
b10100 O
b10000000000000001 "
b10000000000000001 %
b10000000000000001 K
#40
b1 4
b1 6
b1 >
b1 A
b1 D
b1 F
1-
b0 L
b11100 :
b11100 ?
0#
#41
b0 3
b1 1
b1 =
b1 P
b0 9
b0 B
b1111 7
b1111 G
b1 8
b1 E
b0 (
b0 I
b0 T
#42
b0 0
b0 J
b1111 :
b1111 ?
#44
1#
#45
b10100 !
b10100 5
b10100 N
#46
b1 3
b1 (
b1 I
b1 T
#47
b10 &
b10 Q
b10 +
b10 S
b11111111 0
b11111111 J
b11000 ,
b11000 O
b10000000100000001000000001 "
b10000000100000001000000001 %
b10000000100000001000000001 K
#48
b1111 1
b1111 =
b1111 P
b1 2
b1 ;
b1 M
0-
b10 L
0#
#49
b1001 )
b1001 <
b1001 @
b1001 C
b1001 H
b1001 R
#50
b1001 7
b1001 G
b1 9
b1 B
#51
b1010 1
b1010 =
b1010 P
b1010 :
b1010 ?
#52
1#
#53
b11000 !
b11000 5
b11000 N
#54
b1010 )
b1010 <
b1010 @
b1010 C
b1010 H
b1010 R
#55
bx &
bx Q
bx +
bx S
bx *
bx U
bx .
b1011 7
b1011 G
b0 9
b0 B
b11100 ,
b11100 O
bx "
bx %
bx K
#56
b0 2
b0 ;
b0 M
0'
b1 1
b1 =
b1 P
bx L
b1011 :
b1011 ?
0#
#57
bx 4
bx 6
bx >
bx A
bx D
bx F
bx 3
bx )
bx <
bx @
bx C
bx H
bx R
bx (
bx I
bx T
#58
bx 1
bx =
bx P
bx 8
bx E
bx 7
bx G
bx 9
bx B
bx 0
bx J
#59
bx :
bx ?
#60
1#
#61
b11100 !
b11100 5
b11100 N
#63
b100000 ,
b100000 O
#64
0#
#68
1#
#69
b100000 !
b100000 5
b100000 N
#71
b100100 ,
b100100 O
#72
0#
#76
1#
#77
b100100 !
b100100 5
b100100 N
#79
b101000 ,
b101000 O
#80
0#
#84
1#
#85
b101000 !
b101000 5
b101000 N
#87
b101100 ,
b101100 O
#88
0#
#92
1#
#93
b101100 !
b101100 5
b101100 N
#95
b110000 ,
b110000 O
#96
0#
#100
1#
#101
b110000 !
b110000 5
b110000 N
#103
b110100 ,
b110100 O
#104
0#
#108
1#
#109
b110100 !
b110100 5
b110100 N
#111
b111000 ,
b111000 O
#112
0#
#116
1#
#117
b111000 !
b111000 5
b111000 N
#119
b111100 ,
b111100 O
#120
0#
#124
1#
#125
b111100 !
b111100 5
b111100 N
#127
b1000000 ,
b1000000 O
#128
0#
#132
1#
#133
b1000000 !
b1000000 5
b1000000 N
#135
b1000100 ,
b1000100 O
#136
0#
#140
1#
#141
b1000100 !
b1000100 5
b1000100 N
#143
b1001000 ,
b1001000 O
#144
0#
#148
1#
#149
b1001000 !
b1001000 5
b1001000 N
#151
b1001100 ,
b1001100 O
#152
0#
#156
1#
#157
b1001100 !
b1001100 5
b1001100 N
#159
b1010000 ,
b1010000 O
#160
0#
#164
1#
#165
b1010000 !
b1010000 5
b1010000 N
#167
b1010100 ,
b1010100 O
#168
0#
#172
1#
#173
b1010100 !
b1010100 5
b1010100 N
#175
b1011000 ,
b1011000 O
#176
0#
#180
1#
#181
b1011000 !
b1011000 5
b1011000 N
#183
b1011100 ,
b1011100 O
#184
0#
#188
1#
#189
b1011100 !
b1011100 5
b1011100 N
#191
b1100000 ,
b1100000 O
#192
0#
#196
1#
#197
b1100000 !
b1100000 5
b1100000 N
#199
b1100100 ,
b1100100 O
#200
0#
#204
1#
#205
b1100100 !
b1100100 5
b1100100 N
#207
b1101000 ,
b1101000 O
#208
0#
#212
1#
#213
b1101000 !
b1101000 5
b1101000 N
#215
b1101100 ,
b1101100 O
#216
0#
#220
1#
#221
b1101100 !
b1101100 5
b1101100 N
#223
b1110000 ,
b1110000 O
#224
0#
#228
1#
#229
b1110000 !
b1110000 5
b1110000 N
#231
b1110100 ,
b1110100 O
#232
0#
#236
1#
#237
b1110100 !
b1110100 5
b1110100 N
#239
b1111000 ,
b1111000 O
#240
0#
#244
1#
#245
b1111000 !
b1111000 5
b1111000 N
#247
b1111100 ,
b1111100 O
#248
0#
#252
1#
#253
b1111100 !
b1111100 5
b1111100 N
#255
b10000000 ,
b10000000 O
#256
0#
#260
1#
#261
b10000000 !
b10000000 5
b10000000 N
#263
b10000100 ,
b10000100 O
#264
0#
#268
1#
#269
b10000100 !
b10000100 5
b10000100 N
#271
b10001000 ,
b10001000 O
#272
0#
#276
1#
#277
b10001000 !
b10001000 5
b10001000 N
#279
b10001100 ,
b10001100 O
#280
0#
#284
1#
#285
b10001100 !
b10001100 5
b10001100 N
#287
b10010000 ,
b10010000 O
#288
0#
#292
1#
#293
b10010000 !
b10010000 5
b10010000 N
#295
b10010100 ,
b10010100 O
#296
0#
#300
1#
#301
b10010100 !
b10010100 5
b10010100 N
#303
b10011000 ,
b10011000 O
#304
0#
#308
1#
#309
b10011000 !
b10011000 5
b10011000 N
#311
b10011100 ,
b10011100 O
#312
0#
#316
1#
#317
b10011100 !
b10011100 5
b10011100 N
#319
b10100000 ,
b10100000 O
#320
0#
#324
1#
#325
b10100000 !
b10100000 5
b10100000 N
#327
b10100100 ,
b10100100 O
#328
0#
#332
1#
#333
b10100100 !
b10100100 5
b10100100 N
#335
b10101000 ,
b10101000 O
#336
0#
#340
1#
#341
b10101000 !
b10101000 5
b10101000 N
#343
b10101100 ,
b10101100 O
#344
0#
#348
1#
#349
b10101100 !
b10101100 5
b10101100 N
#351
b10110000 ,
b10110000 O
#352
0#
#356
1#
#357
b10110000 !
b10110000 5
b10110000 N
#359
b10110100 ,
b10110100 O
#360
0#
#364
1#
#365
b10110100 !
b10110100 5
b10110100 N
#367
b10111000 ,
b10111000 O
#368
0#
#372
1#
#373
b10111000 !
b10111000 5
b10111000 N
#375
b10111100 ,
b10111100 O
#376
0#
#380
1#
#381
b10111100 !
b10111100 5
b10111100 N
#383
b11000000 ,
b11000000 O
#384
0#
#388
1#
#389
b11000000 !
b11000000 5
b11000000 N
#391
b11000100 ,
b11000100 O
#392
0#
#396
1#
#397
b11000100 !
b11000100 5
b11000100 N
#399
b11001000 ,
b11001000 O
#400
0#
#404
1#
#405
b11001000 !
b11001000 5
b11001000 N
#407
b11001100 ,
b11001100 O
#408
0#
#412
1#
#413
b11001100 !
b11001100 5
b11001100 N
#415
b11010000 ,
b11010000 O
#416
0#
#420
1#
#421
b11010000 !
b11010000 5
b11010000 N
#423
b11010100 ,
b11010100 O
#424
0#
#428
1#
#429
b11010100 !
b11010100 5
b11010100 N
#431
b11011000 ,
b11011000 O
#432
0#
#436
1#
#437
b11011000 !
b11011000 5
b11011000 N
#439
b11011100 ,
b11011100 O
#440
0#
#444
1#
#445
b11011100 !
b11011100 5
b11011100 N
#447
b11100000 ,
b11100000 O
#448
0#
#452
1#
#453
b11100000 !
b11100000 5
b11100000 N
#455
b11100100 ,
b11100100 O
#456
0#
#460
1#
#461
b11100100 !
b11100100 5
b11100100 N
#463
b11101000 ,
b11101000 O
#464
0#
#468
1#
#469
b11101000 !
b11101000 5
b11101000 N
#471
b11101100 ,
b11101100 O
#472
0#
#476
1#
#477
b11101100 !
b11101100 5
b11101100 N
#479
b11110000 ,
b11110000 O
#480
0#
#484
1#
#485
b11110000 !
b11110000 5
b11110000 N
#487
b11110100 ,
b11110100 O
#488
0#
#492
1#
#493
b11110100 !
b11110100 5
b11110100 N
#495
b11111000 ,
b11111000 O
#496
0#
#500
1#
#501
b11111000 !
b11111000 5
b11111000 N
#503
b11111100 ,
b11111100 O
