CPU.v
`include "REG_FILE.v"
`include "ALU.v"

module cpu(PC, INSTRUCTION, CLK, RESET);

    input CLK,RESET;
    output reg [31:0] PC;//need to store the value of pc to be output 
    input [31:0] INSTRUCTION; 

    wire WRITEENABLE;
    wire [31:0] PC_PLUS4;//this wire holds the PC+4 adder's output until the next posedge 
    wire [31:0] PC_NEXT_JUMP;//holds the value of next pc in a jump/beq instruction
    reg [31:0] PC_NEXT;
    wire [2:0] ALUOP;

    wire COMPLEMENT_FLAG;//control signal for the mux 1 (where complemented or original value is choosen)
    wire IMMEDIATE_FALG;//control signal for the mux 2 (where immediate value or mux 1's out is choosen)
    wire BRANCH_FALG;//control signal for the mux3 (choose between immediate value added PC or PC+4)
    wire JUMP_FALG;//control signal for the mux4 (choose between immediate value added PC or mux3 out)
    
    wire [7:0] REGOUT1;//registerfile out 1
    wire [7:0] REGOUT2;//registerfile out 2
    wire [7:0] COMPLEMENTED_OUT;//output from the 2's complementor
    reg [7:0] COMPLEMENT_MUX_OUT;//output from the mux 1 (complement)
    reg [7:0] IMMEDIATE_MUX_OUT;//output from the mux 2 (immediate)
    wire [7:0] IMMEDIATE;//immediate value from the control unit 
    wire [7:0] ALU_RESULT;
    wire ZERO;//to be used in BEQ instructions
    wire ZERO_AND_BRANCHFLAG;//to be used as a mux input 
    reg MUX_3_OUT;//to be used as the fourth mux's input
    wire [31:0] JUMP_IMMEDIATE_FINAL;
    wire [31:0] JUMP_IMMEDIATE_RAW;    

    //register file inputs
    wire [2:0] READREG1;
    wire [2:0] READREG2;
    wire [2:0] WRITEREG;

    //setting the wires for immediate values and reg_file inputs with relevent bits of the instruction
    assign WRITEREG = INSTRUCTION[23:16];
    assign READREG1 = INSTRUCTION[15:8];
    assign READREG2 = INSTRUCTION[7:0];
    assign IMMEDIATE = INSTRUCTION[7:0];
    assign JUMP_IMMEDIATE_RAW = INSTRUCTION[23:16];
	
    //instantiating the modules control unit, pc adder, reg file, alu and the complementor
    control_unit ctrlUnit(INSTRUCTION,WRITEENABLE,ALUOP,COMPLEMENT_FLAG,IMMEDIATE_FALG);
    pc_adder pcNext(PC,PC_PLUS4);
    pc_adder_jump pcJumpNext(PC_PLUS4,PC_NEXT_JUMP,JUMP_IMMEDIATE_FINAL);
    reg_file regFile(ALU_RESULT,REGOUT1,REGOUT2,WRITEREG,READREG1,READREG2, WRITEENABLE, CLK, RESET);
    alu ALU(REGOUT1,IMMEDIATE_MUX_OUT,ALU_RESULT,ALUOP,ZERO);
    twosComplement complementor(REGOUT2,COMPLEMENTED_OUT);
    
    //assigning the mux3 control (choose between immediate value added PC or PC+4)
    assign ZERO_AND_BRANCHFLAG = ZERO & BRANCH_FALG;

    //left shifting by 2 (as the jump instruction immediate offset comes in terms of instructions) is achived by wiring
    //sign is extended by concatenating the MSB 24 times
    assign JUMP_IMMEDIATE_FINAL= {{22{JUMP_IMMEDIATE_RAW[7]}},JUMP_IMMEDIATE_RAW[7:0],2'b00};

    always @ (REGOUT2,COMPLEMENTED_OUT,COMPLEMENT_FLAG) begin//mux 1 (where complemented or original value is choosen)
        case (COMPLEMENT_FLAG)
            0 : COMPLEMENT_MUX_OUT <= REGOUT2;//original value
            1 : COMPLEMENT_MUX_OUT <= COMPLEMENTED_OUT;//complemented value
        endcase
    end

    always @ (COMPLEMENT_MUX_OUT,IMMEDIATE_FALG,IMMEDIATE) begin//mux 2 (where immediate value or mux 1's out is choosen)
        case (IMMEDIATE_FALG)
            0 : IMMEDIATE_MUX_OUT <= COMPLEMENT_MUX_OUT;//previous mux out
            1 : IMMEDIATE_MUX_OUT <= IMMEDIATE;//immediate value
        endcase
    end
    
    always @ (PC_NEXT_JUMP,BRANCH_FALG,PC_PLUS4) begin//mux 3 (where immediate value or mux 1's out is choosen)
        case (BRANCH_FALG)
            0 : MUX_3_OUT <= PC_PLUS4;//PC + 4 value
            1 : MUX_3_OUT <= PC_NEXT_JUMP;//immediate value added PC
        endcase
    end
    
    always @ (MUX_3_OUT,JUMP_FALG,PC_NEXT_JUMP) begin//mux 4 (where immediate value or mux 1's out is choosen)
        case (JUMP_FALG)
            0 : PC_NEXT <= MUX_3_OUT;//previous mux out
            1 : PC_NEXT <= PC_NEXT_JUMP;//immediate value added PC
        endcase
    end

    always @ (posedge CLK) begin//synchronous reset of the pc
        case(RESET)
            0 : PC <= #1 PC_NEXT;
            1 : PC <= #1 32'b0;
        endcase
    end

endmodule


module control_unit(INSTRUCTION,WRITEENABLE,ALUOP,COMPLEMENT_FLAG,IMMEDIATE_FALG);
    
    input [31:0] INSTRUCTION;
    output reg WRITEENABLE;
    output reg [2:0] ALUOP;
    output reg COMPLEMENT_FLAG;
    output reg IMMEDIATE_FALG;
    output reg BRANCH_FALG;
    output reg JUMP_FALG;

    wire [7:0] opcode;
    assign opcode = INSTRUCTION[31:24];

    always @ (opcode) begin//control unit decisions ; with simulated decoding delays
        case (opcode)
            8'b0000_0000 : begin//register is written into and an immediate value is chosen in a loadi instruction
                WRITEENABLE <= #1 1;
                COMPLEMENT_FLAG <= #1 0;//doesn't matter 0 or 1
                IMMEDIATE_FALG <=#1 1;
                BRANCH_FALG <=#1 0;
                JUMP_FALG <=#1 0;
                ALUOP <= #1 3'b000;//loadi==>foward                  
            end
            8'b0000_0001 : begin// uncomplemented register file output two is fowarded to be written     
                WRITEENABLE <= #1 1;
                COMPLEMENT_FLAG <= #1 0;
                IMMEDIATE_FALG <= #1 0;
                BRANCH_FALG <=#1 0;
                JUMP_FALG <=#1 0;
                ALUOP <= #1 3'b000;//mov==>foward 
            end
            8'b0000_0010 : begin//uncomplemented values are added             
                WRITEENABLE <= #1 1;
                COMPLEMENT_FLAG <= #1 0;
                IMMEDIATE_FALG <= #1 0;
                BRANCH_FALG <=#1 0;
                JUMP_FALG <=#1 0;
                ALUOP <= #1 3'b001;//add==>add
            end
            8'b0000_0011 : begin//complemented values are added    
                WRITEENABLE <= #1 1;
                COMPLEMENT_FLAG <= #1 1;
                IMMEDIATE_FALG <= #1 0;
                BRANCH_FALG <=#1 0;
                JUMP_FALG <=#1 0;
                ALUOP <= #1 3'b001;//sub==>add
            end
            8'b0000_0100 : begin//uncomplemented reg values are andded 
                WRITEENABLE <= #1 1;
                COMPLEMENT_FLAG <= #1 0;
                IMMEDIATE_FALG <= #1 0;
                BRANCH_FALG <=#1 0;
                JUMP_FALG <=#1 0;
                ALUOP <= #1 3'b010;//and==>and  
            end
            8'b0000_0101 : begin//uncomplemented values are orred         
                WRITEENABLE <= #1 1;
                COMPLEMENT_FLAG <= #1 0;
                IMMEDIATE_FALG <= #1 0;
                BRANCH_FALG <=#1 0;
                JUMP_FALG <=#1 0;
                ALUOP <= #1 3'b011;//or==>or    
            end
            8'b0000_0110 : begin//jump instruction ; alu's behaviour doesn't matter
                WRITEENABLE <= #1 0;
                COMPLEMENT_FLAG <= #1 0;
                IMMEDIATE_FALG <= #1 0;
                BRANCH_FALG <=#1 0;
                JUMP_FALG <=#1 1;//jump is set to 1
                ALUOP <= #1 3'b000;    
            end
            8'b0000_0111 : begin//beq instruction ; alu performs an add operation with the complemented data2 value         
                WRITEENABLE <= #1 0;
                COMPLEMENT_FLAG <= #1 1;
                IMMEDIATE_FALG <= #1 0;
                BRANCH_FALG <=#1 1;//branch flag is set to 0
                JUMP_FALG <=#1 0;
                ALUOP <= #1 3'b010;//beq==>add
            end
            default : begin              
                WRITEENABLE <= #1 0;
                COMPLEMENT_FLAG <= #1 0;
                IMMEDIATE_FALG <= #1 0;
                ALUOP <= #1 3'b000;    
            end
        endcase  
    end

endmodule

module twosComplement(REGOUT2,COMPLEMENTED_OUT);

    input signed [7:0] REGOUT2;
    output signed [7:0] COMPLEMENTED_OUT;

    assign #1 COMPLEMENTED_OUT = - REGOUT2;

endmodule

module pc_adder(PC,PC_PLUS4);
    input [31:0] PC;
    output [31:0] PC_PLUS4;

    assign #2 PC_PLUS4 = PC + 32'b0100;//MSBs are filled with 0s

endmodule

module pc_adder_jump(PC_PLUS4,PC_NEXT_JUMP,JUMP_IMMEDIATE_FINAL);
    input [31:0] PC_PLUS4;
    input [31:0] JUMP_IMMEDIATE_FINAL;
    output [31:0] PC_NEXT_JUMP;

    assign#2 PC_NEXT_JUMP = PC_PLUS4 + JUMP_IMMEDIATE_FINAL;

endmodule

ALU.v
/*module testbed;//for testing the alu

    reg [7:0] DATA1,DATA2;
    reg [2:0] SELECT; //creating registers and wires
    wire [7:0] RESULT;

    initial begin
        $monitor($time,"select = %b data1 = %b data2 = %b result : %b",SELECT,DATA1,DATA2,RESULT);//monitering the changes in result
        $dumpfile("alu_wavedata.vcd");//wavedata dumpfile to be examined with GTKwave
        $dumpvars(0,testbed);//dumpng all the variables in the testbed 
    end

    alu myALU(DATA1,DATA2,RESULT,SELECT);//instanciating the alu module

    initial begin
        DATA1 = 8'b1000_0001;
        DATA2 = 8'b0100_1110;
    end

    initial begin
        #10
        SELECT = 3'b001;//add signal
        DATA1 = 8'b0000_0001;
        DATA2 = 8'b0000_0011;
    end

    initial begin
        #15
        SELECT = 3'b010;//and signal
        DATA1 = 8'b1101_0101;
        DATA2 = 8'b1110_1010;
    end

    initial begin
        #20
        SELECT = 3'b011;//or signal
        DATA1 = 8'b0000_0001;
        DATA2 = 8'b0000_0010;
    end
    
    initial begin
        #25
        SELECT = 3'b000;
        DATA1 = 8'b1000_0001;
        DATA2 = 8'b0111_1110;
    end

    initial begin//finishing the simulation
        #100 $finish;
    end

endmodule*/

module alu(DATA1,DATA2,RESULT,SELECT,ZERO);

    input  [7:0] DATA1 ;
    input  [7:0] DATA2 ;//defining inputs and outputs all wires exept for the result register
    input  [2:0] SELECT ;
    output reg [7:0] RESULT;//has to be register type, as RESULT is assigned values in an always @ block
    output reg ZERO;//for outputting whether inputs are equal or not

    wire [7:0] forward_out,add_out,and_out,or_out;//wires inside the alu

    FORWARD Forward(DATA2,forward_out);//instantiating modules with individual output wires for each
    ADD Add(DATA1,DATA2,add_out);
    AND And(DATA1,DATA2,and_out) ;
    OR Or(DATA1,DATA2,or_out) ;

    always @ (add_out) begin //setting out for beq instructions
        if ( add_out == 0 )
            ZERO = 1 ;     
        else
            ZERO = 0 ;
    end

   always @ (SELECT,forward_out,add_out,and_out,or_out) begin//run whenever inputs are changed

    case (SELECT)

    3'b000 :  RESULT = forward_out;//assigning the coresponding outputs acording to the SELECT signal
    3'b001 :  RESULT = add_out;
    3'b010 :  RESULT = and_out;
    3'b011 :  RESULT = or_out;
    default :  RESULT =forward_out;
    
    endcase

    end

endmodule
    
module FORWARD(DATA2,RESULT);//module for forwarding the data from port two to RESULT

    input [7:0] DATA2 ;
    output [7:0] RESULT;

    assign #1 RESULT = DATA2;//continuous assigning of valules to the wire RESULT with an artifitial delay

endmodule

module ADD(DATA1,DATA2,RESULT);//module to add two 8bit data values

    input [7:0] DATA1 ;
    input [7:0] DATA2 ;
    output [7:0] RESULT;

    assign #2 RESULT = DATA1 + DATA2;//addiing the data and continuesly assigning the wire RESULT with an artifitial delay

endmodule

module AND(DATA1,DATA2,RESULT) ;//module for bitwise and operation

    input [7:0] DATA1 ;
    input [7:0] DATA2 ;
    output [7:0] RESULT;

    assign #1 RESULT = DATA1 & DATA2;//ANDing the data and continuesly assigning the wire RESULT with an artifitial delay

endmodule

module OR(DATA1,DATA2,RESULT) ;//module for bitwise or operation

    input [7:0] DATA1 ;
    input [7:0] DATA2 ;
    output [7:0] RESULT;

    assign #1 RESULT = DATA1 | DATA2;//ORing the data and continuesly assigning the wire RESULT with an artifitial delay

endmodule

module SUB(DATA1,DATA2,RESULT) ;//module for bitwise or operation

    input [7:0] DATA1 ;
    input [7:0] DATA2 ;
    output [7:0] RESULT;

    assign #1 RESULT = DATA1 - DATA2;//ORing the data and continuesly assigning the wire RESULT with an artifitial delay

endmodule

REG_FILE.v
/*
module testbed;//for testing the reg_file
    reg [7:0] IN;
    reg [2:0] INADDRESS,OUT1ADDRESS,OUT2ADDRESS;//creating registers and wires
    reg WRITE, CLK, RESET;
    wire [7:0] OUT1,OUT2;

    initial begin
        $monitor($time," OUT1 : %b OUT2 : %b",OUT1,OUT2);//monitering the changes in results
        $dumpfile("regfile_wavedata.vcd");//wavedata dumpfile to be examined with GTKwave
        $dumpvars(0,testbed);//dumpng all the variables in the testbed 
    end

    reg_file myreg(IN,OUT1,OUT2,INADDRESS,OUT1ADDRESS,OUT2ADDRESS, WRITE, CLK, RESET);//instanciating the register file module


    initial begin//creating a clock signal that flips every 10 time units forever 
        CLK = 1'b0;
        forever #10 CLK = ~CLK;	
    end

    
    initial begin

		Testing the RESET
		-----------------
		The clock goes up at t = 10. Therefore, the registers should be reset t = 10.
		Since reading has a delay of 2 time units, OUT1 and OUT2 should be 0 at t=12.
	
        #5
        RESET = 1;
        WRITE = 0;
        OUT1ADDRESS = 3'b000;
        OUT2ADDRESS = 3'b001; 
        
		
    end

    The register starts to write 8'b00011111 in the register 3'b010 at t=30. Since writing has a delay of 1 time units,
    the value should be written into the register at t=31.When the value of the register is read the OUT1 should be 
    8'b00010001 at t = 33. Since the OUT2ADDRESS did't change the value should be 8'b00000000.

    initial begin 
        #25
        RESET =0;
        WRITE = 1;
        IN = 8'b0001_1111;
        INADDRESS  = 3'b010;
        OUT1ADDRESS = 3'b010;
    end
 
     
    Making sure the register doesn't work at a negative edge of the clock.
    There is a negative edge of the clock at t=40. Even though the WRITE is enabled, the writing process does not take placa.
    So at t = 39+2 = 41 , OUT1 and OUT2 should be 8b'00000000.
    
    
    initial begin 
        #39
        WRITE = 1;
        IN = 8'b0000_1111;
        INADDRESS  = 3'b011;
        OUT1ADDRESS = 3'b011;
    end
    
    
    //Writing to a register and Reading it (using the OUT2)

    initial begin 
        #45
        WRITE = 1;
        IN = 8'b0101_0101;
        INADDRESS  = 3'b100;
		OUT2ADDRESS = 3'b100;
    end
 
	
    initial begin
        #70
        INADDRESS = 3'b010;
        IN = 8'b1111_1111;
        OUT2ADDRESS  = 3'b010;
         
    end
    
  
    initial begin//finishing the simulation
        #100
        $finish;
    end

endmodule
*/

module reg_file(IN,OUT1,OUT2,INADDRESS,OUT1ADDRESS,OUT2ADDRESS, WRITE, CLK, RESET);
    input [7:0] IN;
    output [7:0] OUT1;
    output [7:0] OUT2;
    input [2:0] INADDRESS;//defining inputs and outputs
    input WRITE;
    input CLK;
    input RESET;
    input [2:0] OUT1ADDRESS;
    input [2:0] OUT2ADDRESS;

    reg [7:0] REG_FILE [7:0] ;//creating the registers

    integer i ;

    assign #2 OUT1 = REG_FILE[OUT1ADDRESS] ;//continuously assigning the values in the regisers to output ports with a delay

    assign #2 OUT2 = REG_FILE[OUT2ADDRESS] ;

    always @ (posedge CLK) begin//at the positive edge of the clock signal
        if (RESET) begin//if reset signal is enabled, assign registers to  all zeros
            for (i=0;i<8;i++) 
                REG_FILE[i] <= #2 8'b0000_0000;
        end else if (WRITE) begin//if the reset is not enabled and the write is enabled write IN value to the relevent register
            #1 REG_FILE[INADDRESS] <=  IN;
        end
    end

endmodule

cpu_tb.v
// Computer Architecture (CO224) - Lab 05
// Design: Testbench of Integrated CPU of Simple Processor
// Author: Kisaru Liyanage
//Group : 12

`include "CPU.v"

module cpu_tb;

    reg CLK, RESET;
    wire [31:0] PC;
    wire [31:0] INSTRUCTION;

    reg [7:0] instr_mem[0:1023];//instruction memory array

    //taking 4 contiguous memory locations to create an instruction
    assign #2 INSTRUCTION = {instr_mem[PC],instr_mem[PC+32'b0001],instr_mem[PC+32'b0010],instr_mem[PC+32'b0011]};
    
    /* 
    ------------------------
     SIMPLE INSTRUCTION MEM
    ------------------------
    */
    
    // TODO: Initialize an array of registers (8x1024) named 'instr_mem' to be used as instruction memory
    
    // TODO: Create combinational logic to support CPU instruction fetching, given the Program Counter(PC) value 
    //       (make sure you include the delay for instruction fetching here)
    
    initial
    begin
        // Initialize instruction memory with the set of instructions you need execute on CPU
        
        // METHOD 1: manually loading instructions to instr_mem
        /*
        {instr_mem[10'd3], instr_mem[10'd2], instr_mem[10'd1], instr_mem[10'd0]} = 32'b00000000000001000000000000000101;
        {instr_mem[10'd7], instr_mem[10'd6], instr_mem[10'd5], instr_mem[10'd4]} = 32'b00000000000000100000000000001001;
        {instr_mem[10'd11], instr_mem[10'd10], instr_mem[10'd9], instr_mem[10'd8]} = 32'b00000010000001100000010000000010;
        */
        // METHOD 2: loading instr_mem content from instr_mem.mem file
        $readmemb("instr_mem.mem", instr_mem);
    end
    
    /* 
    -----
     CPU
    -----
    */
    cpu mycpu(PC, INSTRUCTION, CLK, RESET);

    initial
    begin
    
        // generate files needed to plot the waveform using GTKWave
        $dumpfile("cpu_wavedata.vcd");
		$dumpvars(0, cpu_tb);
        
        CLK = 1'b0;

        //creating a reset pulse of 5 time units
        RESET = 1'b1;
        #5
        RESET = 1'b0;
        
        // TODO: Reset the CPU (by giving a pulse to RESET signal) to start the program execution
        
        // finish simulation after some time
        #500
        $finish;
        
    end
    
    // clock signal generation
    always
        #4 CLK = ~CLK;
        

endmodule

cpu_wavedata.vcd
$date
	Fri Oct 30 22:22:11 2020
$end
$version
	Icarus Verilog
$end
$timescale
	1s
$end
$scope module cpu_tb $end
$var wire 32 ! PC [31:0] $end
$var wire 32 " INSTRUCTION [31:0] $end
$var reg 1 # CLK $end
$var reg 1 $ RESET $end
$scope module mycpu $end
$var wire 1 % BRANCH_FALG $end
$var wire 1 # CLK $end
$var wire 32 & INSTRUCTION [31:0] $end
$var wire 1 ' JUMP_FALG $end
$var wire 1 $ RESET $end
$var wire 1 ( ZERO_AND_BRANCHFLAG $end
$var wire 1 ) ZERO $end
$var wire 3 * WRITEREG [2:0] $end
$var wire 1 + WRITEENABLE $end
$var wire 8 , REGOUT2 [7:0] $end
$var wire 8 - REGOUT1 [7:0] $end
$var wire 3 . READREG2 [2:0] $end
$var wire 3 / READREG1 [2:0] $end
$var wire 32 0 PC_PLUS4 [31:0] $end
$var wire 32 1 PC_NEXT_JUMP [31:0] $end
$var wire 32 2 JUMP_IMMEDIATE_RAW [31:0] $end
$var wire 32 3 JUMP_IMMEDIATE_FINAL [31:0] $end
$var wire 1 4 IMMEDIATE_FALG $end
$var wire 8 5 IMMEDIATE [7:0] $end
$var wire 1 6 COMPLEMENT_FLAG $end
$var wire 8 7 COMPLEMENTED_OUT [7:0] $end
$var wire 8 8 ALU_RESULT [7:0] $end
$var wire 3 9 ALUOP [2:0] $end
$var reg 8 : COMPLEMENT_MUX_OUT [7:0] $end
$var reg 8 ; IMMEDIATE_MUX_OUT [7:0] $end
$var reg 1 < MUX_3_OUT $end
$var reg 32 = PC [31:0] $end
$var reg 32 > PC_NEXT [31:0] $end
$scope module ALU $end
$var wire 8 ? DATA2 [7:0] $end
$var wire 8 @ or_out [7:0] $end
$var wire 8 A forward_out [7:0] $end
$var wire 8 B and_out [7:0] $end
$var wire 8 C add_out [7:0] $end
$var wire 3 D SELECT [2:0] $end
$var wire 8 E DATA1 [7:0] $end
$var reg 8 F RESULT [7:0] $end
$var reg 1 ) ZERO $end
$scope module Add $end
$var wire 8 G DATA2 [7:0] $end
$var wire 8 H RESULT [7:0] $end
$var wire 8 I DATA1 [7:0] $end
$upscope $end
$scope module And $end
$var wire 8 J DATA2 [7:0] $end
$var wire 8 K RESULT [7:0] $end
$var wire 8 L DATA1 [7:0] $end
$upscope $end
$scope module Forward $end
$var wire 8 M DATA2 [7:0] $end
$var wire 8 N RESULT [7:0] $end
$upscope $end
$scope module Or $end
$var wire 8 O DATA2 [7:0] $end
$var wire 8 P RESULT [7:0] $end
$var wire 8 Q DATA1 [7:0] $end
$upscope $end
$upscope $end
$scope module complementor $end
$var wire 8 R REGOUT2 [7:0] $end
$var wire 8 S COMPLEMENTED_OUT [7:0] $end
$upscope $end
$scope module ctrlUnit $end
$var wire 32 T INSTRUCTION [31:0] $end
$var wire 8 U opcode [7:0] $end
$var reg 3 V ALUOP [2:0] $end
$var reg 1 W BRANCH_FALG $end
$var reg 1 6 COMPLEMENT_FLAG $end
$var reg 1 4 IMMEDIATE_FALG $end
$var reg 1 X JUMP_FALG $end
$var reg 1 + WRITEENABLE $end
$upscope $end
$scope module pcJumpNext $end
$var wire 32 Y JUMP_IMMEDIATE_FINAL [31:0] $end
$var wire 32 Z PC_PLUS4 [31:0] $end
$var wire 32 [ PC_NEXT_JUMP [31:0] $end
$upscope $end
$scope module pcNext $end
$var wire 32 \ PC [31:0] $end
$var wire 32 ] PC_PLUS4 [31:0] $end
$upscope $end
$scope module regFile $end
$var wire 1 # CLK $end
$var wire 8 ^ IN [7:0] $end
$var wire 3 _ INADDRESS [2:0] $end
$var wire 8 ` OUT1 [7:0] $end
$var wire 3 a OUT1ADDRESS [2:0] $end
$var wire 8 b OUT2 [7:0] $end
$var wire 3 c OUT2ADDRESS [2:0] $end
$var wire 1 $ RESET $end
$var wire 1 + WRITE $end
$var integer 32 d i [31:0] $end
$upscope $end
$upscope $end
$upscope $end
$enddefinitions $end
#0
$dumpvars
bx d
bx c
bx b
bx a
bx `
bx _
bx ^
bx ]
bx \
bx [
bx Z
bx00 Y
xX
xW
bx V
bx U
bx T
bx S
bx R
bx Q
bx P
bx O
bx N
bx M
bx L
bx K
bx J
bx I
bx H
bx G
bx F
bx E
bx D
bx C
bx B
bx A
bx @
bx ?
bx >
bx =
x<
bx ;
bx :
bx 9
bx 8
bx 7
x6
bx 5
x4
bx00 3
b0xxxxxxxx 2
bx 1
bx 0
bx /
bx .
bx -
bx ,
x+
bx *
x)
x(
z'
bx &
z%
1$
0#
bx "
bx !
$end
#4
b1000 d
1#
#5
b0 !
b0 =
b0 \
0$
#7
b0 *
b0 _
b1 /
b1 a
b0 .
b0 c
b0 3
b0 Y
b0 5
b0 2
b1 U
b100 0
b100 Z
b100 ]
b1000000000000000100000000 "
b1000000000000000100000000 &
b1000000000000000100000000 T
#8
b0 9
b0 D
b0 V
0X
0W
04
06
1+
0#
#9
b0 ;
b0 ?
b0 G
b0 J
b0 M
b0 O
b0 :
b0 -
b0 E
b0 I
b0 L
b0 Q
b0 `
b0 ,
b0 R
b0 b
b100 1
b100 [
#10
b0 8
b0 F
b0 ^
b0 @
b0 P
b0 A
b0 N
b0 B
b0 K
b0 7
b0 S
#11
1)
b0 C
b0 H
#12
1#
#13
bx !
bx =
bx \
#15
bx *
bx _
bx /
bx a
bx .
bx c
bx00 3
bx00 Y
bx 5
b0xxxxxxxx 2
bx U
bx 0
bx Z
bx ]
bx "
bx &
bx T
#16
0+
0#
#17
bx ;
bx ?
bx G
bx J
bx M
bx O
bx :
bx -
bx E
bx I
bx L
bx Q
bx `
bx ,
bx R
bx b
bx 1
bx [
#18
bx 8
bx F
bx ^
bx B
bx K
bx A
bx N
bx @
bx P
bx 7
bx S
#19
0(
0)
bx C
bx H
